hbase_thrift/Hbase.thrift
hbase_thrift/__init__.py
hbase_thrift/_version.py
hbase_thrift/batch.py
hbase_thrift/connection.py
hbase_thrift/elasticsearch_helper.py
hbase_thrift/hbase_es.py
hbase_thrift/hbase_helper.py
hbase_thrift/pool.py
hbase_thrift/table.py
hbase_thrift/test.py
hbase_thrift/util.py
hbase_thrift_py_sdk-2.3.6.data/data/README.md
hbase_thrift_py_sdk-2.3.6.data/data/requirements.txt
hbase_thrift_py_sdk-2.3.6.dist-info/LICENSE.txt
hbase_thrift_py_sdk-2.3.6.dist-info/METADATA
hbase_thrift_py_sdk-2.3.6.dist-info/WHEEL
hbase_thrift_py_sdk-2.3.6.dist-info/top_level.txt
hbase_thrift_py_sdk-2.3.6.dist-info/RECORD
