Metadata-Version: 2.1
Name: hbase-thrift-py-sdk
Version: 2.3.6
Summary: Use elaticsearch to search hbase
Home-page: http://gitlab.weyesns.com/jcsp/library/hbase-thrift-py-sdk
License: MIT
Platform: any
